LICENSE
MANIFEST.in
ReadMe.md
setup.py
Strategies/__init__.py
Tests/Tests.py
Tests/__init__.py
Tests/Strategies/BollingerBands.py
Tests/Strategies/Movingaverage_cd.py
Tests/Strategies/UnitTestStrategy.py
Tests/Strategies/UnitTestStrategyIndicator.py
Tests/Strategies/__init__.py
tradingmachine/Asset.py
tradingmachine/BTHarness.py
tradingmachine/Error.py
tradingmachine/Utils.py
tradingmachine/__init__.py
tradingmachine/sharedLogger.py
tradingmachine.egg-info/PKG-INFO
tradingmachine.egg-info/SOURCES.txt
tradingmachine.egg-info/dependency_links.txt
tradingmachine.egg-info/requires.txt
tradingmachine.egg-info/top_level.txt
tradingmachine.egg-info/tradingmachine.sublime-project
tradingmachine.egg-info/tradingmachine.sublime-workspace
tradingmachine/DataFeed/CSVDataFeed.py
tradingmachine/DataFeed/DataFeedBase.py
tradingmachine/DataFeed/PriceRecord.py
tradingmachine/DataFeed/__init__.py
tradingmachine/Indicators/Indicator.py
tradingmachine/Indicators/__init__.py
tradingmachine/MarketSimulator/MarketSimulator.py
tradingmachine/MarketSimulator/__init__.py
tradingmachine/Strategy/Strategy.py
tradingmachine/Strategy/__init__.py