Metadata-Version: 1.0
Name: tradingmachine
Version: 0.1.7
Summary: A backtester for financial algorithms.
Home-page: https://gitlab.com/chinux23/tradingmachine
Author: Chen Huang
Author-email: chinux@gmail.com
License: BSD
Platform: UNKNOWN
Classifier: Development Status :: 1 - Planning
Classifier: License :: OSI Approved :: BSD License
Classifier: Natural Language :: English
Classifier: Programming Language :: Python
Classifier: Programming Language :: Python :: 3.3
Classifier: Operating System :: OS Independent
Classifier: Intended Audience :: Science/Research
Classifier: Topic :: Office/Business :: Financial
Classifier: Topic :: Scientific/Engineering :: Information Analysis
Classifier: Topic :: System :: Distributed Computing
